<?xml version="1.0" encoding="utf-8"?>
<!-- https://learn.microsoft.com/en-us/dotnet/fundamentals/package-validation/diagnostic-ids -->
<Suppressions xmlns:xsi="http://www.w3.org/2001/XMLSchema-instance" xmlns:xsd="http://www.w3.org/2001/XMLSchema">
  <Suppression>
    <DiagnosticId>PKV004</DiagnosticId>
    <Target>.NETCoreApp,Version=v2.0</Target>
  </Suppression>
  <Suppression>
    <DiagnosticId>PKV004</DiagnosticId>
    <Target>.NETFramework,Version=v4.6.1</Target>
  </Suppression>
  <Suppression>
    <DiagnosticId>PKV004</DiagnosticId>
    <Target>.NETFramework,Version=v4.6.2</Target>
  </Suppression>
  <Suppression>
    <DiagnosticId>PKV004</DiagnosticId>
    <Target>.NETFramework,Version=v4.6.3</Target>
  </Suppression>
  <Suppression>
    <DiagnosticId>PKV004</DiagnosticId>
    <Target>.NETStandard,Version=v2.0</Target>
  </Suppression>
  <Suppression>
    <DiagnosticId>PKV004</DiagnosticId>
    <Target>Tizen,Version=v4.0</Target>
  </Suppression>
  <Suppression>
    <DiagnosticId>PKV004</DiagnosticId>
    <Target>UAP,Version=v10.0.15064</Target>
  </Suppression>
  <Suppression>
    <DiagnosticId>PKV004</DiagnosticId>
    <Target>Xamarin.PlayStation3,Version=v0.0</Target>
  </Suppression>
  <Suppression>
    <DiagnosticId>PKV004</DiagnosticId>
    <Target>Xamarin.PlayStation4,Version=v0.0</Target>
  </Suppression>
  <Suppression>
    <DiagnosticId>PKV004</DiagnosticId>
    <Target>Xamarin.PlayStationVita,Version=v0.0</Target>
  </Suppression>
  <Suppression>
    <DiagnosticId>PKV004</DiagnosticId>
    <Target>Xamarin.Xbox360,Version=v0.0</Target>
  </Suppression>
  <Suppression>
    <DiagnosticId>PKV004</DiagnosticId>
    <Target>Xamarin.XboxOne,Version=v0.0</Target>
  </Suppression>
  <!--
  Since we are dropping the .net 8 and retarrgetting to .net 9, we need to suppress the following errors. 
  The comparison ref/net.8 with ref/netstandard2.0 is not valid anymore.
  -->
  <Suppression>
    <DiagnosticId>CP0008</DiagnosticId>
    <Target>T:Microsoft.Build.Framework.AssemblyLoadingContext</Target>
    <Left>ref/net8.0/Microsoft.Build.Framework.dll</Left>
    <Right>ref/netstandard2.0/Microsoft.Build.Framework.dll</Right>
    <IsBaselineSuppression>true</IsBaselineSuppression>
  </Suppression>
  <Suppression>
    <DiagnosticId>CP0008</DiagnosticId>
    <Target>T:Microsoft.Build.Framework.FeatureStatus</Target>
    <Left>ref/net8.0/Microsoft.Build.Framework.dll</Left>
    <Right>ref/netstandard2.0/Microsoft.Build.Framework.dll</Right>
    <IsBaselineSuppression>true</IsBaselineSuppression>
  </Suppression>
  <Suppression>
    <DiagnosticId>CP0008</DiagnosticId>
    <Target>T:Microsoft.Build.Framework.LoggerVerbosity</Target>
    <Left>ref/net8.0/Microsoft.Build.Framework.dll</Left>
    <Right>ref/netstandard2.0/Microsoft.Build.Framework.dll</Right>
    <IsBaselineSuppression>true</IsBaselineSuppression>
  </Suppression>
  <Suppression>
    <DiagnosticId>CP0008</DiagnosticId>
    <Target>T:Microsoft.Build.Framework.MessageImportance</Target>
    <Left>ref/net8.0/Microsoft.Build.Framework.dll</Left>
    <Right>ref/netstandard2.0/Microsoft.Build.Framework.dll</Right>
    <IsBaselineSuppression>true</IsBaselineSuppression>
  </Suppression>
  <Suppression>
    <DiagnosticId>CP0008</DiagnosticId>
    <Target>T:Microsoft.Build.Framework.Profiler.EvaluationLocationKind</Target>
    <Left>ref/net8.0/Microsoft.Build.Framework.dll</Left>
    <Right>ref/netstandard2.0/Microsoft.Build.Framework.dll</Right>
    <IsBaselineSuppression>true</IsBaselineSuppression>
  </Suppression>
  <Suppression>
    <DiagnosticId>CP0008</DiagnosticId>
    <Target>T:Microsoft.Build.Framework.Profiler.EvaluationPass</Target>
    <Left>ref/net8.0/Microsoft.Build.Framework.dll</Left>
    <Right>ref/netstandard2.0/Microsoft.Build.Framework.dll</Right>
    <IsBaselineSuppression>true</IsBaselineSuppression>
  </Suppression>
  <Suppression>
    <DiagnosticId>CP0008</DiagnosticId>
    <Target>T:Microsoft.Build.Framework.RegisteredTaskObjectLifetime</Target>
    <Left>ref/net8.0/Microsoft.Build.Framework.dll</Left>
    <Right>ref/netstandard2.0/Microsoft.Build.Framework.dll</Right>
    <IsBaselineSuppression>true</IsBaselineSuppression>
  </Suppression>
  <Suppression>
    <DiagnosticId>CP0008</DiagnosticId>
    <Target>T:Microsoft.Build.Framework.TargetBuiltReason</Target>
    <Left>ref/net8.0/Microsoft.Build.Framework.dll</Left>
    <Right>ref/netstandard2.0/Microsoft.Build.Framework.dll</Right>
    <IsBaselineSuppression>true</IsBaselineSuppression>
  </Suppression>
  <Suppression>
    <DiagnosticId>CP0008</DiagnosticId>
    <Target>T:Microsoft.Build.Framework.TargetSkipReason</Target>
    <Left>ref/net8.0/Microsoft.Build.Framework.dll</Left>
    <Right>ref/netstandard2.0/Microsoft.Build.Framework.dll</Right>
    <IsBaselineSuppression>true</IsBaselineSuppression>
  </Suppression>
  <Suppression>
    <DiagnosticId>CP0008</DiagnosticId>
    <Target>T:Microsoft.Build.Framework.TaskParameterMessageKind</Target>
    <Left>ref/net8.0/Microsoft.Build.Framework.dll</Left>
    <Right>ref/netstandard2.0/Microsoft.Build.Framework.dll</Right>
    <IsBaselineSuppression>true</IsBaselineSuppression>
  </Suppression>
  <!--
    https://learn.microsoft.com/en-us/dotnet/fundamentals/apicompat/diagnostic-ids
    Suppress PKV006 for net8.0 (The target framework is dropped in the latest version.)  -->
  <Suppression>
    <DiagnosticId>PKV006</DiagnosticId>
    <Target>net8.0</Target>
  </Suppression>
</Suppressions>
