{
  "author": "Майкрософт",
  "name": "Файл Directory.Build.props MSBuild",
  "description": "Пустой файл Directory.Build.props, который можно использовать для указания свойств MSBuild для всей папки",
  "symbols/inherit/displayName": "Наследовать",
  "symbols/inherit/description": "Если значение равно \"true\", добавляет импорт для ближайшего Directory.Build.props в иерархии каталогов файловой системы. Directory.Build.props не наследуется по умолчанию, поэтому это позволяет создать набор папок настроек по папкам.",
  "symbols/useArtifacts/displayName": "Использовать выходной макет артефактов",
  "symbols/useArtifacts/description": "Если присвоено значение true, добавляется свойство для включения выходного макета артефактов. Это общий шаблон для проектов, которые создают артефакты сборки, например пакеты NuGet, помещаемые в общую папку."
}